revcore/__init__.py
revcore/settings.py
revcore/commands/__init__.py
revcore/commands/init_table.py
revcore/ddb/__init__.py
revcore/ddb/exceptions.py
revcore/ddb/models.py
revcore/django/__init__.py
revcore/django/exceptions.py
revcore/django/filters.py
revcore/django/permissions.py
revcore/django/authentication/__init__.py
revcore/django/authentication/tokens.py
revcore/scripts/__init__.py
revcore/scripts/init_tables.py
revcore/utils/__init__.py
utils/__init__.py
revcore-0.0.3.dist-info/METADATA
revcore-0.0.3.dist-info/WHEEL
revcore-0.0.3.dist-info/top_level.txt
revcore-0.0.3.dist-info/RECORD
